gpustack/__init__.py
gpustack/logging.py
gpustack/main.py
gpustack/security.py
gpustack/api/auth.py
gpustack/api/exceptions.py
gpustack/api/middlewares.py
gpustack/api/responses.py
gpustack/api/types/openai_ext.py
gpustack/assets/model-catalog-modelscope.yaml
gpustack/assets/model-catalog.yaml
gpustack/assets/chat_templates/template_deepseek_vl2.jinja
gpustack/assets/chat_templates/tool_chat_template_deepseekv32.jinja
gpustack/assets/chat_templates/tool_chat_template_llama3.1_json.jinja
gpustack/assets/chat_templates/tool_chat_template_llama3.2_json.jinja
gpustack/assets/metrics_config/metrics_config.yaml
gpustack/client/__init__.py
gpustack/client/generated_clientset.py
gpustack/client/generated_http_client.py
gpustack/client/generated_inference_backend_client.py
gpustack/client/generated_model_client.py
gpustack/client/generated_model_file_client.py
gpustack/client/generated_model_instance_client.py
gpustack/client/generated_user_client.py
gpustack/client/generated_worker_client.py
gpustack/client/worker_manager_clients.py
gpustack/cloud_providers/abstract.py
gpustack/cloud_providers/common.py
gpustack/cloud_providers/digital_ocean.py
gpustack/cloud_providers/user_data.py
gpustack/cmd/__init__.py
gpustack/cmd/db_migration.py
gpustack/cmd/download_tools.py
gpustack/cmd/images.py
gpustack/cmd/prerun.py
gpustack/cmd/reload_config.py
gpustack/cmd/reset_admin_password.py
gpustack/cmd/start.py
gpustack/cmd/version.py
gpustack/codegen/__init__.py
gpustack/codegen/filters.py
gpustack/codegen/generate.py
gpustack/codegen/templates/client.py.jinja
gpustack/codegen/templates/clientset.py.jinja
gpustack/codegen/templates/http_client.py.jinja
gpustack/config/__init__.py
gpustack/config/config.py
gpustack/config/registration.py
gpustack/detectors/base.py
gpustack/detectors/detector_factory.py
gpustack/detectors/custom/custom.py
gpustack/detectors/fastfetch/config_gpu.jsonc
gpustack/detectors/fastfetch/config_system_info.jsonc
gpustack/detectors/fastfetch/fastfetch.py
gpustack-2.0.3.dist-info/METADATA
gpustack-2.0.3.dist-info/WHEEL
gpustack-2.0.3.dist-info/entry_points.txt
gpustack-2.0.3.dist-info/licenses/LICENSE
gpustack-2.0.3.dist-info/RECORD
