Metadata-Version: 2.3
Name: gpustack
Version: 2.0.3
Summary: GPUStack
Author-email: GPUStack Authors <contact@gpustack.ai>
Requires-Python: <3.13,>=3.10
Requires-Dist: aiocache>=0.12.3
Requires-Dist: aiofiles>=23.2.1
Requires-Dist: aiohttp>=3.11.2
Requires-Dist: aiolimiter>=1.2.1
Requires-Dist: aiosqlite>=0.20.0
Requires-Dist: alembic>=1.13.2
Requires-Dist: apscheduler<4.0.0,>=3.10.4
Requires-Dist: argon2-cffi>=23.1.0
Requires-Dist: asyncmy>=0.2.10
Requires-Dist: asyncpg>=0.29.0
Requires-Dist: attrs>=24.2.0
Requires-Dist: blobfile>=3.0.0
Requires-Dist: cachetools>=6.0.0
Requires-Dist: colorama>=0.4.6
Requires-Dist: cryptography>=43.0.0
Requires-Dist: dataclasses-json>=0.6.7
Requires-Dist: fastapi-cdn-host>=0.8.0
Requires-Dist: fastapi>=0.115.0
Requires-Dist: gpustack-runner==0.1.22.post6
Requires-Dist: gpustack-runtime==0.1.38.post4
Requires-Dist: hf-transfer>=0.1.9
Requires-Dist: httpx[socks]>=0.27.0
Requires-Dist: huggingface-hub>=0.32.0
Requires-Dist: importlib-resources>=6.4.0
Requires-Dist: inflection>=0.5.1
Requires-Dist: jinja2>=3.1.6
Requires-Dist: kubernetes-asyncio>=33.1.0
Requires-Dist: kubernetes>=33.1.0
Requires-Dist: lxml==5.2.1
Requires-Dist: modelscope>=1.28
Requires-Dist: msgpack>=1.1.2
Requires-Dist: openai>=1.31.1
Requires-Dist: packaging>=24.1
Requires-Dist: pandas>=2.3.0
Requires-Dist: prometheus-client>=0.20.0
Requires-Dist: psutil>=7.0.0
Requires-Dist: psycopg2-binary>=2.9.10
Requires-Dist: pyarrow<19.0.0,>=18.0.0
Requires-Dist: pydantic-settings>=2.2.1
Requires-Dist: pydantic>=2.11.5
Requires-Dist: pydo>=0.15.0
Requires-Dist: pyjwt>=2.8.0
Requires-Dist: pymysql>=1.1.1
Requires-Dist: pytest-asyncio>=0.23.7
Requires-Dist: python-json-logger>=3.3.0
Requires-Dist: python-multipart>=0.0.17
Requires-Dist: python3-saml==1.16.0
Requires-Dist: pywin32>=308; platform_system == 'Windows'
Requires-Dist: requests>=2.32.3
Requires-Dist: setproctitle>=1.3.3
Requires-Dist: sqlalchemy[asyncio]>=2.0.38
Requires-Dist: sqlmodel>=0.0.18
Requires-Dist: tenacity>=9.0.0
Requires-Dist: transformers!=4.57.0,>=4.51.3
Requires-Dist: truststore>=0.9.1
Requires-Dist: tzdata>=2024.1
Requires-Dist: uvicorn>=0.32.0
Requires-Dist: wmi>=1.5.1; platform_system == 'Windows'
Requires-Dist: xmlsec==1.3.14
Provides-Extra: all
Requires-Dist: bitsandbytes>=0.45.2; extra == 'all'
Requires-Dist: mistral-common[opencv]>=1.4.3; extra == 'all'
Requires-Dist: timm>=1.0.15; extra == 'all'
Requires-Dist: vllm==0.10.1.1; extra == 'all'
Requires-Dist: vox-box==0.0.19; extra == 'all'
Provides-Extra: audio
Requires-Dist: vox-box==0.0.19; extra == 'audio'
Provides-Extra: vllm
Requires-Dist: bitsandbytes>=0.45.2; extra == 'vllm'
Requires-Dist: mistral-common[opencv]>=1.4.3; extra == 'vllm'
Requires-Dist: timm>=1.0.15; extra == 'vllm'
Requires-Dist: vllm==0.10.1.1; extra == 'vllm'
